calculator_riciokzz/__init__.py
calculator_riciokzz/calculator.py
calculator_riciokzz-0.0.3.dist-info/METADATA
calculator_riciokzz-0.0.3.dist-info/WHEEL
calculator_riciokzz-0.0.3.dist-info/licenses/LICENSE
calculator_riciokzz-0.0.3.dist-info/RECORD
