Metadata-Version: 2.1
Name: calculator_riciokzz
Version: 0.0.3
Summary: A calculator which can perform simple algebra.
Author-email: Ričardas Poskrebyševas <ricardas.poskrebysev@gmail.com>
License-File: LICENSE
Classifier: License :: OSI Approved :: MIT License
Classifier: Operating System :: Microsoft :: Windows :: Windows 10
Classifier: Programming Language :: Python :: 3
Requires-Python: >=3.10
